<?xml version="1.0" encoding="UTF-8" standalone="yes"?>
<payment xmlns="http://www.elastic-payments.com/schema/payment" self="https://api-test.wirecard.com:443/engine/rest/merchants/86687a11-3f9b-4f30-be54-8f22998b6177/payments/b684dc00-c550-48e0-b70b-f2b20e4eb72f">
  <merchant-account-id ref="https://api-test.wirecard.com:443/engine/rest/config/merchants/86687a11-3f9b-4f30-be54-8f22998b6177">86687a11-3f9b-4f30-be54-8f22998b6177</merchant-account-id>
  <transaction-id>b684dc00-c550-48e0-b70b-f2b20e4eb72f</transaction-id>
  <request-id>0fdf8e2f-7a42-4cbe-ab65-e2e3100de3c8</request-id>
  <transaction-type>void-original-credit</transaction-type>
  <transaction-state>success</transaction-state>
  <completion-time-stamp>2019-09-02T08:46:33.000Z</completion-time-stamp>
  <statuses>
    <status code="201.0000" description="3d-acquirer:The resource was successfully created." severity="information"/>
  </statuses>
  <requested-amount currency="EUR">1.11</requested-amount>
  <parent-transaction-id>79777c35-2d24-405b-9faf-af3fdab7fdd9</parent-transaction-id>
  <account-holder>
    <first-name>John</first-name>
    <last-name>Doe</last-name>
    <email>john.doe@test.com</email>
    <phone>
    </phone>
    <address>
      <street1>123 anystreet</street1>
      <city>Brantford</city>
      <state>ON</state>
      <country>CA</country>
    </address>
  </account-holder>
  <card-token>
    <token-id>4332596410400007</token-id>
    <masked-account-number>401200******0007</masked-account-number>
  </card-token>
  <ip-address>127.0.0.1</ip-address>
  <payment-methods>
    <payment-method name="creditcard"/>
  </payment-methods>
  <parent-transaction-amount currency="EUR">1.110000</parent-transaction-amount>
  <authorization-code>732290</authorization-code>
  <api-id>elastic-api</api-id>
  <provider-account-id>00000031734B7BC5</provider-account-id>
</payment>