{
  "payment": {
    "statuses": {
      "status": [
        {
          "code": "201.0000",
          "description": "The resource was successfully created.",
          "severity": "information"
        }
      ]
    },
    "notifications": {
      "notification": [
        {
          "url": "{{notification_endpoint}}"
        }
      ]
    },
    "merchant-account-id": {
      "value": "8b99e2dc-c8d0-43b8-9ebb-0a35fa808af7"
    },
    "transaction-id": "6eeb4b5f-8148-497d-80c2-6b35f013c0cf",
    "request-id": "48db1126-8864-4ed3-b07a-5d5e0354960b",
    "transaction-type": "debit",
    "transaction-state": "success",
    "completion-time-stamp": 1572860498000,
    "requested-amount": {
      "value": 10,
      "currency": "EUR"
    },
    "account-holder": {
      "email": "john.doe@example.com",
      "phone": "SK00",
      "address": {
        "street1": "Test Street 123",
        "city": "Test City",
        "country": "SK"
      },
      "first-name": "John",
      "last-name": "Doe"
    },
    "order-detail": "Test Order",
    "payment-methods": {
      "payment-method": [
        {
          "url": "https://buy.boku.com/checkoutidentify/5ulmbpv7qlqqrj3ego3ghdxy/buy.js",
          "name": "carrier-billing"
        }
      ]
    },
    "consumer-id": "Test Consumer",
    "cancel-redirect-url": "https://demoshop-test.wirecard.com/demoshop/#/cancel",
    "fail-redirect-url": "https://demoshop-test.wirecard.com/demoshop/#/error",
    "success-redirect-url": "https://demoshop-test.wirecard.com/demoshop/#/success"
  }
}